leer/__init__.py
leer/__main__.py
leer/syncer.py
leer/version.py
leer/core/__init__.py
leer/core/core_loop.py
leer/core/utils.py
leer/core/chains/__init__.py
leer/core/chains/blockchain.py
leer/core/chains/headers_manager.py
leer/core/core_operations/__init__.py
leer/core/core_operations/blockchain_initialization.py
leer/core/core_operations/core_context.py
leer/core/core_operations/downloading.py
leer/core/core_operations/handle_mining.py
leer/core/core_operations/notifications.py
leer/core/core_operations/process_metadata.py
leer/core/core_operations/process_requests.py
leer/core/core_operations/receiving_assets.py
leer/core/core_operations/sending_assets.py
leer/core/core_operations/sending_metadata.py
leer/core/core_operations/sending_requests.py
leer/core/hash/__init__.py
leer/core/hash/mining_canary.py
leer/core/hash/progpow.py
leer/core/lubbadubdub/__init__.py
leer/core/lubbadubdub/address.py
leer/core/lubbadubdub/constants.py
leer/core/lubbadubdub/ioput.py
leer/core/lubbadubdub/offset_utils.py
leer/core/lubbadubdub/script.py
leer/core/lubbadubdub/transaction.py
leer/core/lubbadubdub/transaction_generation.py
leer/core/lubbadubdub/utils.py
leer/core/parameters/__init__.py
leer/core/parameters/constants.py
leer/core/parameters/dynamic.py
leer/core/parameters/fee_policy.py
leer/core/primitives/__init__.py
leer/core/primitives/block.py
leer/core/primitives/header.py
leer/core/primitives/transaction_skeleton.py
leer/core/storage/__init__.py
leer/core/storage/blocks_storage.py
leer/core/storage/excesses_storage.py
leer/core/storage/headers_storage.py
leer/core/storage/key_value_storage.py
leer/core/storage/lookup_utils.py
leer/core/storage/mempool_tx.py
leer/core/storage/merkle_storage.py
leer/core/storage/storage_space.py
leer/core/storage/txos_storage.py
leer/core/storage/utxo_index_storage.py
leer/core/storage/verification_cache.py
leer/notification/__init__.py
leer/notification/notification_center.py
leer-0.2.5.dist-info/DESCRIPTION.rst
leer-0.2.5.dist-info/METADATA
leer-0.2.5.dist-info/RECORD
leer-0.2.5.dist-info/WHEEL
leer-0.2.5.dist-info/metadata.json
leer-0.2.5.dist-info/top_level.txt
