Metadata-Version: 2.0
Name: leer
Version: 0.2.5
Summary: Leer cryptocurrency (alpha testing)
Home-page: https://github.com/WTRMQDev/leer
Author: Evil Morty, Crez Khansick, Sark Czenchi
Author-email: TetsuwanAtomu@tuta.io
License: UNKNOWN
Platform: UNKNOWN
Classifier: Programming Language :: Python :: 3
Classifier: Development Status :: 4 - Beta
Classifier: Intended Audience :: Developers
Classifier: License :: OSI Approved :: MIT License
Classifier: Operating System :: OS Independent
Requires-Dist: aiohttp
Requires-Dist: aiohttp-remotes
Requires-Dist: jsonrpcserver (==3.5.6)
Requires-Dist: leer-vm (>=1.1)
Requires-Dist: lmdb
Requires-Dist: lnoise
Requires-Dist: progpow (>=0.3)
Requires-Dist: secp256k1-zkp (>=0.14.3)
Requires-Dist: setuptools
Requires-Dist: wheel
